{
  "meta": {
    "restaurant": {
      "slug": "onesta",
      "name": "Onesta",
      "area": "Koramangala",
      "districtSlugs": [
        "onesta-1-bommanahalli-bangalore",
        "onesta-1-electronic-city-bangalore",
        "onesta-1-mahadevapura-bangalore",
        "onesta-1-marathahalli-bangalore",
        "onesta-2-electronic-city-bangalore",
        "onesta-aecs-layout-bangalore",
        "onesta-bannerghatta-road-bangalore",
        "onesta-basaveshwara-nagar-bangalore",
        "onesta-hebbal-bangalore",
        "onesta-hsr",
        "onesta-indiranagar-bangalore",
        "onesta-jp-nagar",
        "onesta-kammanahalli",
        "onesta-kanakapura-road-bangalore",
        "onesta-koramangala-4th-block-bangalore",
        "onesta-koramangala-5th-block-bangalore",
        "onesta-mahadevapura-bangalore",
        "onesta-new-bel-road",
        "onesta-rajarajeshwari-nagar",
        "onesta-yelahanka"
      ]
    },
    "found": true,
    "offerSummary": [
      "[addon] Flat 10% off* — use HDFCINFINIA",
      "[addon] Flat 10% off* — use HDFCCCEMI",
      "[addon] Flat 10% off* — use HDFCDINERS",
      "[addon] Flat ₹200 off — use HDFCCARDS",
      "[addon] Cashback ₹50 — use MBKDINEUPI",
      "[addon] Cashback ₹50 — use MBKDINE",
      "[addon] Cashback ₹50 — use POPUPI",
      "[addon] Cashback 10%* — Swiggy HDFC Bank Credit Card",
      "[addon] Cashback 5%* — Swiggy Ornge HDFC Bank Credit Card"
    ]
  },
  "raw": {
    "restaurantId": "401186",
    "detail": {
      "requestId": "fb7c49c3-acc8-4a60-9d50-6a29005b5e8b",
      "apiTime": "2026-05-17T16:19:12.470271760Z",
      "success": {
        "statusMessage": "done successfully",
        "cards": [
          {
            "card": {
              "card": {
                "@type": "type.googleapis.com/swiggy.presentation.dinersone.v1.EntityInfoWithMasthead",
                "id": "401186",
                "info": {
                  "name": "Onesta",
                  "locationInfo": {
                    "distanceString": "5.9 km",
                    "navigationUrl": "https://www.google.com/maps/dir/?api=1&origin=12.9716,77.5946&destination=12.978657,77.64357999999993&travelmode=driving",
                    "lat": "12.978657",
                    "long": "77.64357999999993",
                    "city": {
                      "name": "Bangalore"
                    },
                    "formattedAddress": "Indiranagar, Bangalore",
                    "additionalInfo": {
                      "cta": {
                        "link": "swiggydiners://collectiondetails/DINEOUT_BRAND_OUTLETS?tags=layout_dineout_brand_outlets&metaMap=%7B%22brandId%22%3A%2211785%22%2C%22restaurant_id%22%3A%22401186%22%2C%22sourcePage%22%3A%22RDP%22%7D&header_title=Outlets",
                        "text": "outlets",
                        "type": "DEEPLINK",
                        "metaInfo": {
                          "ctaImage": "dineout/details/red_arrow_down.png"
                        },
                        "analytics": {
                          "screenName": "DO-Detail",
                          "context": "{\"restId\":\"401186\"}",
                          "objectValue": "outlet_switcher_dropdown",
                          "impressionObjectName": "entity_info_masthead",
                          "clickObjectName": "entity_info_masthead"
                        }
                      }
                    },
                    "displayAreaName": "Indiranagar"
                  },
                  "timingsInfo": {
                    "status": "Open",
                    "message": "till 11PM",
                    "outletTiming": {
                      "infoList": [
                        {
                          "title": "Monday",
                          "subtitle": "11AM - 11PM",
                          "titleColor": "text_high_emphasis",
                          "subtitleColor": "text_high_emphasis"
                        },
                        {
                          "title": "Tuesday",
                          "subtitle": "11AM - 11PM",
                          "titleColor": "text_high_emphasis",
                          "subtitleColor": "text_high_emphasis"
                        },
                        {
                          "title": "Wednesday",
                          "subtitle": "11AM - 11PM",
                          "titleColor": "text_high_emphasis",
                          "subtitleColor": "text_high_emphasis"
                        },
                        {
                          "title": "Thursday",
                          "subtitle": "11AM - 11PM",
                          "titleColor": "text_high_emphasis",
                          "subtitleColor": "text_high_emphasis"
                        },
                        {
                          "title": "Friday",
                          "subtitle": "11AM - 11PM",
                          "titleColor": "text_high_emphasis",
                          "subtitleColor": "text_high_emphasis"
                        },
                        {
                          "title": "Saturday",
                          "subtitle": "11AM - 11PM",
                          "titleColor": "text_high_emphasis",
                          "subtitleColor": "text_high_emphasis"
                        },
                        {
                          "title": "Today",
                          "subtitle": "11AM - 11PM",
                          "titleColor": "primary",
                          "subtitleColor": "primary"
                        }
                      ],
                      "title": "Outlet timings"
                    },
                    "styleInfo": {
                      "titleColor": "positive",
                      "subtitleColor": "text_color_low_emphasis"
                    }
                  },
                  "callDetail": {
                    "title": "Trying to reach the outlet?",
                    "style": {
                      "cornerRadius": {
                        "topLeft": 16,
                        "topRight": 16
                      },
                      "backgroundColour": "#F0F0F5"
                    },
                    "actions": [
                      {
                        "link": "dailer-app?phone=9513736291",
                        "text": "9513736291",
                        "type": "DIALER",
                        "metaInfo": {
                          "ctaImage": "dineout/details/call_no_bg.png"
                        }
                      }
                    ]
                  },
                  "ratingsInfo": {
                    "value": "4.1",
                    "description": "9K ratings",
                    "count": 9200,
                    "countDescription": "9K+ Google ratings",
                    "icon": "dineout/details/google_tag.png",
                    "style": "RATING_STYLE_V2"
                  },
                  "typeInfo": {
                    "type": "ENTITY_TYPE_RESTAURANT",
                    "restaurantType": "RESTAURANT_TYPE_PARTICIPATING"
                  },
                  "style": {
                    "backgroundColour": "#FFFFFF",
                    "cornerRadius": {
                      "topLeft": 16,
                      "topRight": 16,
                      "bottomLeft": 16,
                      "bottomRight": 16
                    },
                    "animationConfig": {
                      "type": "ANIMATION_TYPE_ENTRY_PUSH_DOWN",
                      "startDelay": 250,
                      "duration": 100,
                      "interpolator": "INTERPOLATOR_LINEAR"
                    },
                    "dimension": {
                      "width": {
                        "type": "TYPE_RELATIVE",
                        "value": 1,
                        "reference": "RELATIVE_DIMENSION_REFERENCE_DEVICE_WIDTH"
                      },
                      "height": {
                        "type": "TYPE_RELATIVE",
                        "value": 0.778,
                        "reference": "RELATIVE_DIMENSION_REFERENCE_WIDTH"
                      }
                    }
                  },
                  "favourite": {
                    "entityLotte": {
                      "frequencyCapping": 2,
                      "image": "favourite-image",
                      "lotteFiles": [
                        {
                          "type": "LOTTIE_TYPE_FAVOURITE",
                          "lotte": "favourite-lottie"
                        },
                        {
                          "type": "LOTTIE_TYPE_NON_FAVOURITE",
                          "lotte": "non-favourite-lottie"
                        }
                      ]
                    },
                    "accessibility": {
                      "altText": "favourite alt text",
                      "altTextCta": "favourite alt text cta"
                    }
                  },
                  "share": {
                    "entityLotte": {
                      "frequencyCapping": 3,
                      "image": "share-image",
                      "lotteFiles": [
                        {
                          "type": "LOTTIE_TYPE_SHARE",
                          "lotte": "share-lottie"
                        }
                      ]
                    },
                    "shareUrl": "Hey, I think you will love Onesta, Indiranagar, Bangalore on Swiggy Dineout https://swiggy.onelink.me/BVRZ?af_dp=swiggydiners%3A%2F%2Fdetails%2F401186%3Fsource%3Dsharing Happy dining!",
                    "accessibility": {
                      "altText": "share alt text",
                      "altTextCta": "share alt text cta"
                    }
                  },
                  "entityAttributes": {
                    "restaurantEntityAttributes": {
                      "outlets": {},
                      "cuisines": [
                        "Pizza",
                        "Beverages"
                      ],
                      "costForTwo": "₹800 for two"
                    }
                  },
                  "callout": {
                    "badge": {
                      "backgroundColor": "#FFFFFF",
                      "icon": {
                        "creativeId": "dineout/dineoutrewards/DC_Mnemonic.png"
                      },
                      "animationConfig": {
                        "type": "ANIMATION_TYPE_EASE_IN"
                      },
                      "borderGradient": [
                        "#2B885B",
                        "#FFFFFF"
                      ]
                    },
                    "info": {
                      "info": "Earn & Redeem 2X DineCash",
                      "color": "sub_brands_dine_cash_primary",
                      "font": "FONT_NAME_V2_BODY3_NEUTRAL_BOLD"
                    },
                    "background": "#E9FFF4",
                    "animationConfig": {
                      "type": "ANIMATION_TYPE_ENTRY_SLIDE_LEFT_RIGHT"
                    }
                  }
                },
                "masthead": {
                  "files": [
                    {
                      "type": "IMAGE",
                      "id": "2022-08-18T02:31:42.787",
                      "name": "ambience",
                      "url": "v1660789905/jrwcddcfkyt4fiyrfatd.jpg"
                    },
                    {
                      "type": "IMAGE",
                      "id": "2022-08-18T02:31:47.077",
                      "name": "ambience",
                      "url": "v1660789909/hgrzel4cmwwdh7pgopu8.jpg"
                    },
                    {
                      "type": "IMAGE",
                      "id": "2022-08-18T02:31:50.967",
                      "name": "ambience",
                      "url": "v1660789913/wzmg0iqbl1bpbnuvrfn5.jpg"
                    },
                    {
                      "type": "IMAGE",
                      "id": "2022-08-18T02:31:55.051",
                      "name": "ambience",
                      "url": "v1660789918/hn93hnqsqp4hu0tllez0.jpg"
                    },
                    {
                      "type": "IMAGE",
                      "id": "2022-08-18T02:32:42.973",
                      "url": "v1660789965/yxurqq07huvbgssipl22.jpg"
                    },
                    {
                      "type": "IMAGE",
                      "id": "2022-08-18T02:32:46.976",
                      "url": "v1660789969/mngbuwbmwlsljwpuazsd.jpg"
                    },
                    {
                      "type": "IMAGE",
                      "id": "2022-08-18T02:32:50.764",
                      "url": "v1660789973/ndfpnzfoiy7w0m8gd0r8.jpg"
                    },
                    {
                      "type": "IMAGE",
                      "id": "2022-08-18T02:32:54.489",
                      "url": "v1660789977/jq76em8tu2bb5hppklbn.jpg"
                    },
                    {
                      "type": "IMAGE",
                      "id": "2022-08-18T02:32:59.089",
                      "url": "v1660789981/wv3ofskixufyls7d2vqf.jpg"
                    },
                    {
                      "type": "IMAGE",
                      "id": "2022-08-18T02:33:02.629",
                      "url": "v1660789985/ywrfdveuogv0mstdzogo.jpg"
                    }
                  ],
                  "cta": {
                    "link": "swiggydiners://gallery/401186",
                    "type": "DEEPLINK"
                  },
                  "cornerRadius": {
                    "bottomLeft": 24,
                    "bottomRight": 24
                  },
                  "autoScrollConfig": {
                    "isScrollEnabled": true,
                    "autoScrollDuration": 3,
                    "autoScrollResetDuration": 5
                  }
                }
              }
            }
          },
          {
            "card": {
              "card": {
                "@type": "type.googleapis.com/swiggy.presentation.dinersone.v1.DealAndOfferInfo",
                "dayWiseOfferInfo": [
                  {
                    "segment": {
                      "id": "OFFERS_FOR_YOU",
                      "title": "Offers for you",
                      "isSelected": true,
                      "analyticsInfo": {
                        "screenName": "DO-Detail",
                        "context": "{\"offer_day\":\"offers_for_you\"}",
                        "objectValue": "401186",
                        "impressionObjectName": "offer_day"
                      }
                    },
                    "tabsOfferInfo": {
                      "offersTab": [
                        {
                          "tabInfo": {
                            "id": "PREBOOK",
                            "title": "Pre-booking offers",
                            "isSelected": true,
                            "analyticsInfo": {
                              "screenName": "DO-Detail",
                              "context": "{\"offer_type\":\"deals\",\"offer_title\":\"Pre-booking offers\"}",
                              "objectValue": "401186",
                              "clickObjectName": "offer_panel_offer_tab_click"
                            }
                          },
                          "tabOffers": {
                            "offers": [
                              {
                                "type": "Pre-Book",
                                "title": "Flat 50% off on Total Bill",
                                "cta": {
                                  "link": "swiggydiners://login",
                                  "text": "LOGIN TO BUY DEALS",
                                  "type": "primary"
                                },
                                "isAvailable": true,
                                "analytics": {
                                  "screenName": "DO-Detail",
                                  "context": "{\"offer_type\":\"Pre-Book\",\"offer_title\":\"Flat 50% off on Total Bill\",\"offer_subtext\":\"\",\"special_callout\":\"dineout/OneExclusive.png\",\"offer_position\":1,\"offer_count\":3}",
                                  "objectValue": "401186",
                                  "impressionObjectName": "offer_panel_offer_item_impression",
                                  "clickObjectName": "offer_panel_offer_item_click"
                                },
                                "textInfo": {
                                  "info": "Flat 50% off on Total Bill"
                                },
                                "offerTheme": {
                                  "logo": "dineout/details/discountwidget/One_Exclusive_upd.png"
                                },
                                "offerCallout": [
                                  {
                                    "logo": "dineout/OneExclusive.png"
                                  }
                                ]
                              },
                              {
                                "type": "Pre-Book",
                                "title": "Flat 30% off on Total Bill",
                                "cta": {
                                  "link": "swiggydiners://login",
                                  "text": "LOGIN TO BUY DEALS",
                                  "type": "primary"
                                },
                                "isAvailable": true,
                                "analytics": {
                                  "screenName": "DO-Detail",
                                  "context": "{\"offer_type\":\"Pre-Book\",\"offer_title\":\"Flat 30% off on Total Bill\",\"offer_subtext\":\"\",\"special_callout\":\"dineout/OneExclusive.png\",\"offer_position\":2,\"offer_count\":3}",
                                  "objectValue": "401186",
                                  "impressionObjectName": "offer_panel_offer_item_impression",
                                  "clickObjectName": "offer_panel_offer_item_click"
                                },
                                "textInfo": {
                                  "info": "Flat 30% off on Total Bill"
                                },
                                "offerTheme": {
                                  "logo": "dineout/details/discountwidget/One_Exclusive_upd.png"
                                },
                                "offerCallout": [
                                  {
                                    "logo": "dineout/OneExclusive.png"
                                  }
                                ]
                              },
                              {
                                "type": "Pre-Book",
                                "title": "Flat 20% off on Total Bill",
                                "cta": {
                                  "link": "swiggydiners://login",
                                  "text": "LOGIN TO BUY DEALS",
                                  "type": "primary"
                                },
                                "isAvailable": true,
                                "analytics": {
                                  "screenName": "DO-Detail",
                                  "context": "{\"offer_type\":\"Pre-Book\",\"offer_title\":\"Flat 20% off on Total Bill\",\"offer_subtext\":\"\",\"special_callout\":\"dineout/OneExclusive.png\",\"offer_position\":3,\"offer_count\":3}",
                                  "objectValue": "401186",
                                  "impressionObjectName": "offer_panel_offer_item_impression",
                                  "clickObjectName": "offer_panel_offer_item_click"
                                },
                                "textInfo": {
                                  "info": "Flat 20% off on Total Bill"
                                },
                                "offerTheme": {
                                  "logo": "dineout/details/discountwidget/One_Exclusive_upd.png"
                                },
                                "offerCallout": [
                                  {
                                    "logo": "dineout/OneExclusive.png"
                                  }
                                ]
                              }
                            ],
                            "dotScrollBar": {
                              "activeColor": "#FF5200",
                              "inactiveColor": "#02060C",
                              "activeSize": 6,
                              "inactiveMediumSize": 4,
                              "inactiveSmallSize": 4,
                              "dotSpacing": 4,
                              "windowSize": 5
                            }
                          }
                        }
                      ],
                      "tabStyle": {
                        "selectedBgColor": "color_background_primary_inverse",
                        "unselectedBgColor": "color_background_secondary",
                        "selectedTextColor": "text_color_highest_emphasis_inverse",
                        "unselectedTextColor": "text_highest_emphasis",
                        "selectedBorderColor": "white",
                        "unselectedBorderColor": "black",
                        "selectTitleFont": "FONT_NAME_V2_BODY2_NEUTRAL_BOLD",
                        "unselectTitleFont": "FONT_NAME_V2_BODY2_NEUTRAL_MEDIUM",
                        "selectSubTitleFont": "FONT_NAME_HEADER_H3",
                        "unselectSubTitleFont": "FONT_NAME_HEADER_H4",
                        "singleTabTitleFont": "FONT_NAME_HEADER_H4",
                        "singleTabBgColor": "grey"
                      },
                      "cornerRadius": {
                        "topLeft": 30,
                        "topRight": 30,
                        "bottomLeft": 30,
                        "bottomRight": 30
                      },
                      "tabCornerRadius": {
                        "topLeft": 10,
                        "topRight": 30,
                        "bottomLeft": 30,
                        "bottomRight": 10
                      }
                    },
                    "addOnOffer": {
                      "title": "ADD-ON OFFERS",
                      "offers": [
                        {
                          "title": "Flat 10% off*",
                          "tnc": {
                            "title": "Offer terms & conditions",
                            "texts": [
                              "Apply the coupon code HDFCINFINIA to avail the offer",
                              "Applicable twice per user per calendar month",
                              "User will get a maximum discount of ₹500 per transaction",
                              "Offer is available only for HDFC Bank Infinia Credit Cardholders",
                              "Transaction amount (amount after deduction of restaurant discounts) of ₹3500 or more payable using an HDFC Bank Infinia Credit Card are eligible for the discount",
                              "Other T&Cs may apply"
                            ]
                          },
                          "description": "use HDFCINFINIA",
                          "secondarySubtext": {
                            "title": "Use coupon code HDFCINFINIA | Avail on final payable amount of ₹3500 or more"
                          },
                          "offerLogo": {
                            "logo": "MARKETING_BANNERS/IMAGES/OFFERS/2026/4/27/a89c7389-3b12-43e8-a0ca-f345638a66c7_"
                          },
                          "analytics": {
                            "screenName": "DO-Detail",
                            "context": "{\"additional_offer_title\":\"Flat 10% off*\",\"additional_offer_subtitle\":\"use HDFCINFINIA\",\"additional_offer_type\":\"addon\",\"additional_offer_position\":1,\"additional_offer_count\":9}",
                            "objectValue": "401186",
                            "impressionObjectName": "offer_panel_addon_offer_item_impression",
                            "clickObjectName": "offer_panel_addon_offer_item_click"
                          }
                        },
                        {
                          "title": "Flat 10% off*",
                          "tnc": {
                            "title": "Offer terms & conditions",
                            "texts": [
                              "Apply the coupon code HDFCCCEMI to avail the offer",
                              "Applicable once per user per calendar month",
                              "User will get a maximum discount of ₹500 per transaction",
                              "Offer is available only for HDFC Bank Credit Card EMI transactions",
                              "Transaction amount (amount after deduction of restaurant discounts) of ₹3500 or more payable using HDFC Bank Credit Card EMI payment are eligible for the discount",
                              "The offer is an instant discount and will be provided upfront at the time of purchase",
                              "Refer the given link for detailed terms and conditions of EMI transactions - hdfcbank.com/personal/borrow/popular-loans/easy-emi/easyemi-on-consumer-durables",
                              "Other T&Cs may apply"
                            ]
                          },
                          "description": "use HDFCCCEMI",
                          "secondarySubtext": {
                            "title": "Use coupon code HDFCCCEMI | Avail on final payable amount of ₹3500 or more"
                          },
                          "offerLogo": {
                            "logo": "MARKETING_BANNERS/IMAGES/OFFERS/2026/4/29/171de65d-20a5-43a4-ad76-91765635391c_"
                          },
                          "analytics": {
                            "screenName": "DO-Detail",
                            "context": "{\"additional_offer_title\":\"Flat 10% off*\",\"additional_offer_subtitle\":\"use HDFCCCEMI\",\"additional_offer_type\":\"addon\",\"additional_offer_position\":2,\"additional_offer_count\":9}",
                            "objectValue": "401186",
                            "impressionObjectName": "offer_panel_addon_offer_item_impression",
                            "clickObjectName": "offer_panel_addon_offer_item_click"
                          }
                        },
                        {
                          "title": "Flat 10% off*",
                          "tnc": {
                            "title": "Offer terms & conditions",
                            "texts": [
                              "Apply the coupon code HDFCDINERS to avail the offer",
                              "Applicable twice per user per calendar month",
                              "User will get a maximum discount of ₹400 per transaction",
                              "Offer is available only for HDFC Bank Diners Club Black/Biz Black Credit Cardholders",
                              "Transaction amount (amount after deduction of restaurant discounts) of ₹3000 or more payable using HDFC Bank Diners Club Black/Biz Black Credit Card are eligible for the discount",
                              "Other T&Cs may apply"
                            ]
                          },
                          "description": "use HDFCDINERS",
                          "secondarySubtext": {
                            "title": "Use coupon code HDFCDINERS | Avail on final payable amount of ₹3000 or more"
                          },
                          "offerLogo": {
                            "logo": "MARKETING_BANNERS/IMAGES/OFFERS/2026/4/27/a2d19ccb-7b28-4786-aca8-d990ef69e4cc_"
                          },
                          "analytics": {
                            "screenName": "DO-Detail",
                            "context": "{\"additional_offer_title\":\"Flat 10% off*\",\"additional_offer_subtitle\":\"use HDFCDINERS\",\"additional_offer_type\":\"addon\",\"additional_offer_position\":3,\"additional_offer_count\":9}",
                            "objectValue": "401186",
                            "impressionObjectName": "offer_panel_addon_offer_item_impression",
                            "clickObjectName": "offer_panel_addon_offer_item_click"
                          }
                        },
                        {
                          "title": "Flat ₹200 off",
                          "tnc": {
                            "title": "Offer terms & conditions",
                            "texts": [
                              "Apply the coupon code HDFCCARDS to avail the offer",
                              "Applicable twice per user per calendar month",
                              "User wili get a flat ₹200 discount per transaction",
                              "Offer is available for all HDFC Bank Credit Cardholders except HDFC Bank Infinia & Diners Club Black Credit Cards",
                              "Not valid on Swiggy HDFC Bank Credit Card",
                              "Transaction amount (amount after deduction of restaurant discounts) of ₹2000 or more payable using HDFC Bank Credit Card are eligible for the discount",
                              "Other T&Cs may apply"
                            ]
                          },
                          "description": "use HDFCCARDS",
                          "secondarySubtext": {
                            "title": "Use coupon code HDFCCARDS | Avail on final payable amount of ₹2000 or more"
                          },
                          "offerLogo": {
                            "logo": "MARKETING_BANNERS/IMAGES/OFFERS/2026/4/27/b9217d65-e29a-476f-9d42-f9fd19f8d1cf_"
                          },
                          "analytics": {
                            "screenName": "DO-Detail",
                            "context": "{\"additional_offer_title\":\"Flat ₹200 off\",\"additional_offer_subtitle\":\"use HDFCCARDS\",\"additional_offer_type\":\"addon\",\"additional_offer_position\":4,\"additional_offer_count\":9}",
                            "objectValue": "401186",
                            "impressionObjectName": "offer_panel_addon_offer_item_impression",
                            "clickObjectName": "offer_panel_addon_offer_item_click"
                          }
                        },
                        {
                          "title": "Cashback ₹50",
                          "tnc": {
                            "title": "Offer terms & conditions",
                            "texts": [
                              "Apply the coupon code MBKDINEUPI to avail the offer",
                              "Applicable once per user during the offer period",
                              "Transaction amount (amount after deduction of restaurant discounts) of ₹1500 or more payable using MobiKwik UPI are eligible for cashback",
                              "Cashback can be claimed through a Scratch card on the MobiKwik app in the rewards section & the Scratch card will be valid for 7 days only",
                              "Other T&Cs may apply"
                            ]
                          },
                          "description": "use MBKDINEUPI",
                          "secondarySubtext": {
                            "title": "Use coupon code MBKDINEUPI | Avail on final payable amount of ₹1500 or more"
                          },
                          "offerLogo": {
                            "logo": "MARKETING_BANNERS/IMAGES/OFFERS/2026/4/27/ac59c31b-d38d-484d-96a9-92b330794aa9_"
                          },
                          "analytics": {
                            "screenName": "DO-Detail",
                            "context": "{\"additional_offer_title\":\"Cashback ₹50\",\"additional_offer_subtitle\":\"use MBKDINEUPI\",\"additional_offer_type\":\"addon\",\"additional_offer_position\":5,\"additional_offer_count\":9}",
                            "objectValue": "401186",
                            "impressionObjectName": "offer_panel_addon_offer_item_impression",
                            "clickObjectName": "offer_panel_addon_offer_item_click"
                          }
                        },
                        {
                          "title": "Cashback ₹50",
                          "tnc": {
                            "title": "Offer terms & conditions",
                            "texts": [
                              "Apply the coupon code MBKDINE to avail the offer",
                              "Applicable once per user during the offer period",
                              "Transaction amount (amount after deduction of restaurant discounts) of ₹1500 or more payable using MobiKwik Wallet are eligible for cashback",
                              "Cashback can be claimed through a Scratch card on the MobiKwik app in the rewards section & the Scratch card will be valid for 7 days only",
                              "Other T&Cs may apply"
                            ]
                          },
                          "description": "use MBKDINE",
                          "secondarySubtext": {
                            "title": "Use coupon code MBKDINE | Avail on final payable amount of ₹1500 or more"
                          },
                          "offerLogo": {
                            "logo": "MARKETING_BANNERS/IMAGES/OFFERS/2026/4/27/e72241b7-4f46-4c50-b56f-b0696f450fc1_"
                          },
                          "analytics": {
                            "screenName": "DO-Detail",
                            "context": "{\"additional_offer_title\":\"Cashback ₹50\",\"additional_offer_subtitle\":\"use MBKDINE\",\"additional_offer_type\":\"addon\",\"additional_offer_position\":6,\"additional_offer_count\":9}",
                            "objectValue": "401186",
                            "impressionObjectName": "offer_panel_addon_offer_item_impression",
                            "clickObjectName": "offer_panel_addon_offer_item_click"
                          }
                        },
                        {
                          "title": "Cashback ₹50",
                          "tnc": {
                            "title": "Offer terms & conditions",
                            "texts": [
                              "Apply the coupon code POPUPI to avail the offer",
                              "Applicable once per user during the offer period",
                              "Transaction amount (amount after deduction of restaurant discounts) of ₹999 or more payable using POP UPI are eligible for cashback",
                              "The customer will redeem POP Coins for cashback",
                              "The customer will get cashback in their POP Cashback Zone",
                              "Other T&Cs may apply"
                            ]
                          },
                          "description": "use POPUPI",
                          "secondarySubtext": {
                            "title": "Use coupon code POPUPI | Avail on final payable amount of ₹999 or more"
                          },
                          "offerLogo": {
                            "logo": "MARKETING_BANNERS/IMAGES/OFFERS/2026/5/6/f0e1f551-8392-490b-b744-c33aa0a17477_"
                          },
                          "analytics": {
                            "screenName": "DO-Detail",
                            "context": "{\"additional_offer_title\":\"Cashback ₹50\",\"additional_offer_subtitle\":\"use POPUPI\",\"additional_offer_type\":\"addon\",\"additional_offer_position\":7,\"additional_offer_count\":9}",
                            "objectValue": "401186",
                            "impressionObjectName": "offer_panel_addon_offer_item_impression",
                            "clickObjectName": "offer_panel_addon_offer_item_click"
                          }
                        },
                        {
                          "title": "Cashback 10%*",
                          "tnc": {
                            "title": "Offer terms & conditions",
                            "texts": [
                              "Valid only on Swiggy HDFC Bank Credit Card or Swiggy Blck HDFC Bank Credit Card",
                              "Monthly cashback limit of ₹1500 on Swiggy spends",
                              "Cashback will be processed in the next statement cycle",
                              "Other T&Cs may apply"
                            ]
                          },
                          "description": "Swiggy HDFC Bank Credit Card",
                          "secondarySubtext": {
                            "title": "Avail on final payable amount of ₹249 or more"
                          },
                          "offerLogo": {
                            "logo": "MARKETING_BANNERS/IMAGES/OFFERS/2026/4/28/05619bca-252d-4dd1-b136-26f43f54b68d_"
                          },
                          "analytics": {
                            "screenName": "DO-Detail",
                            "context": "{\"additional_offer_title\":\"Cashback 10%*\",\"additional_offer_subtitle\":\"Swiggy HDFC Bank Credit Card\",\"additional_offer_type\":\"addon\",\"additional_offer_position\":8,\"additional_offer_count\":9}",
                            "objectValue": "401186",
                            "impressionObjectName": "offer_panel_addon_offer_item_impression",
                            "clickObjectName": "offer_panel_addon_offer_item_click"
                          }
                        },
                        {
                          "title": "Cashback 5%*",
                          "tnc": {
                            "title": "Offer terms & conditions",
                            "texts": [
                              "Valid only on Swiggy Ornge HDFC Bank Credit Card",
                              "Applicable on a minimum net transaction value of ₹249",
                              "Monthly cashback limit of ₹1500 on Swiggy spends",
                              "Cashback will be processed in the next statement cycle",
                              "Other T&Cs may apply"
                            ]
                          },
                          "description": "Swiggy Ornge HDFC Bank Credit Card",
                          "secondarySubtext": {
                            "title": "Avail on final payable amount of ₹249 or more"
                          },
                          "offerLogo": {
                            "logo": "MARKETING_BANNERS/IMAGES/OFFERS/2026/3/16/1526a46c-c05f-4c13-86bf-142fdec229ad_"
                          },
                          "analytics": {
                            "screenName": "DO-Detail",
                            "context": "{\"additional_offer_title\":\"Cashback 5%*\",\"additional_offer_subtitle\":\"Swiggy Ornge HDFC Bank Credit Card\",\"additional_offer_type\":\"addon\",\"additional_offer_position\":9,\"additional_offer_count\":9}",
                            "objectValue": "401186",
                            "impressionObjectName": "offer_panel_addon_offer_item_impression",
                            "clickObjectName": "offer_panel_addon_offer_item_click"
                          }
                        }
                      ],
                      "dotScrollBar": {
                        "activeColor": "#FF5200",
                        "inactiveColor": "#02060C",
                        "activeSize": 4,
                        "inactiveMediumSize": 3,
                        "inactiveSmallSize": 3,
                        "dotSpacing": 4,
                        "windowSize": 3
                      },
                      "autoScrollConfig": {
                        "isScrollEnabled": true,
                        "autoScrollDuration": 3,
                        "autoScrollResetDuration": 3
                      }
                    },
                    "dineCashInfo": {
                      "offers": [
                        {
                          "title": "20% cashback",
                          "cta": {
                            "link": "swiggydiners://login",
                            "text": "LOGIN TO PAY BILL",
                            "type": "primary"
                          },
                          "description": "on every bill payment",
                          "isAvailable": true,
                          "offerLogo": {
                            "logo": "dineout/dineoutrewards/DC_Mnemonic.png"
                          },
                          "analytics": {
                            "screenName": "DO-Detail",
                            "context": "{\"additional_offer_title\":\"20% cashback\",\"additional_offer_subtitle\":\"on every bill payment\",\"additional_offer_type\":\"dinecash\",\"additional_offer_position\":1,\"additional_offer_count\":1}",
                            "objectValue": "401186",
                            "impressionObjectName": "offer_panel_dinecash_offer_item_impression",
                            "clickObjectName": "offer_panel_dinecash_offer_item_click"
                          },
                          "offerTheme": {
                            "logo": "dineout/details/discountwidget/DineCashSplit.png"
                          },
                          "offerTooltip": {
                            "title": {
                              "info": "Flat 20% Cashback",
                              "color": "text_highest_emphasis",
                              "font": "FONT_NAME_V2_BODY1_NEUTRAL_BOLD"
                            },
                            "description": {
                              "info": "Earn & use 2X DineCash at select restaurants",
                              "color": "text_low_emphasis",
                              "font": "FONT_NAME_V2_OVERLINE_MEDIUM"
                            },
                            "iconImage": "dineout/loyalty/dinecashTooltip2XIcon.png",
                            "frequency": {
                              "entityId": "rdp-dinecash-tooltip-1",
                              "maxCount": 3,
                              "cappingInfo": {
                                "cappingEnabled": true,
                                "cappingMode": "VIEW"
                              }
                            },
                            "analytics": {
                              "screenName": "DO-Detail",
                              "context": "{\"subtitle\":\"Earn \\u0026 use 2X DineCash at select restaurants\",\"title\":\"Flat 20% Cashback\"}",
                              "objectValue": "401186",
                              "impressionObjectName": "impression-tooltip",
                              "clickObjectName": "cross-tooltip"
                            }
                          }
                        }
                      ],
                      "nudge": {
                        "content": {
                          "contentBlock": {
                            "subtext": {
                              "info": "Earn & Redeem 2X DineCash",
                              "color": "text_color_highest_emphasis_inverse",
                              "font": "FONT_NAME_V2_OVERLINE_NEUTRAL_MEDIUM"
                            },
                            "icon": {
                              "url": "dineout/loyalty/DC2XRDP.png",
                              "position": "POSITION_CENTER_LEFT",
                              "width": {
                                "value": 70
                              },
                              "height": {
                                "value": 10
                              }
                            },
                            "containerStyle": {
                              "width": 32,
                              "height": 32,
                              "cornerRadius": {
                                "bottomLeft": 20,
                                "bottomRight": 20
                              },
                              "background": {
                                "color": "#2E644A",
                                "backgroundColor": "#00FF00"
                              },
                              "chevron": {
                                "chevronType": "CHEVRON_TYPE_ARROW",
                                "position": "POSITION_TOP_LEFT",
                                "color": "#2E644A"
                              }
                            },
                            "position": "POSITION_TOP",
                            "subtextIcon": {
                              "url": "dineout/loyalty/infoFilled.png",
                              "position": "POSITION_CENTER_RIGHT",
                              "width": {
                                "value": 16
                              },
                              "height": {
                                "value": 16
                              }
                            },
                            "textIconSeparator": true
                          }
                        },
                        "position": "POSITION_TOP",
                        "analytics": {
                          "screenName": "DO-Detail",
                          "context": "{\"rest_id\":\"401186\",\"banner_text\":\"Earn \\u0026 Redeem 2X DineCash\",\"cashback_perc\":\"20\",\"cashback_available\":\"0\"}",
                          "objectValue": "cashback-benefit-callout",
                          "impressionObjectName": "cashback-callout"
                        },
                        "cta": {
                          "link": "swiggy://externalWidget?banner_type=IMAGE&card_type=HALF_CARD&url=dineout/DO_SF/Dc2xHC.png&ratio=0.830556&dismissable=true&backgroundTransparency=false&auto_dismiss=true",
                          "type": "DEEPLINK"
                        }
                      }
                    }
                  }
                ],
                "gradientStyle": {
                  "colours": [
                    "#F0FCF7",
                    "#EBF8F3"
                  ],
                  "gradientAngle": 270
                },
                "headerStyle": {
                  "padding": {
                    "bottom": 8
                  },
                  "titleColor": "text_color_highest_emphasis",
                  "titleFontName": "FONT_NAME_BODY_B1_MED"
                },
                "padding": {
                  "left": 12,
                  "top": 24,
                  "right": 12
                },
                "type": "DEAL_AND_OFFER_INFO_TYPE_PILL_TAB_V2",
                "scrollAnchor": {
                  "id": "offer"
                }
              }
            }
          },
          {
            "card": {
              "card": {
                "@type": "type.googleapis.com/swiggy.presentation.dinersone.v1.RestaurantHighlights",
                "title": "Popular dishes",
                "element": [
                  "Tiramisu, Nutella Falls",
                  "Rice bowl",
                  "Naanizza",
                  "chicken ",
                  "overload pizza",
                  "overload pizza"
                ],
                "content": [
                  {
                    "info": "Tiramisu, Nutella Falls",
                    "icon": "dineout/details/popular_dishes.png"
                  },
                  {
                    "info": "Rice bowl",
                    "icon": "dineout/details/popular_dishes.png"
                  },
                  {
                    "info": "Naanizza",
                    "icon": "dineout/details/popular_dishes.png"
                  },
                  {
                    "info": "chicken ",
                    "icon": "dineout/details/popular_dishes.png"
                  },
                  {
                    "info": "overload pizza",
                    "icon": "dineout/details/popular_dishes.png"
                  },
                  {
                    "info": "overload pizza",
                    "icon": "dineout/details/popular_dishes.png"
                  }
                ],
                "rowCount": 3,
                "colCount": 2,
                "scrollAnchor": {
                  "id": "menu"
                }
              }
            }
          },
          {
            "card": {
              "card": {
                "@type": "type.googleapis.com/swiggy.gandalf.widgets.v2.StaggeredGrid",
                "info": [
                  {
                    "imageCardInfo": {
                      "id": "2022-08-18T02:31:42.787",
                      "imageId": "v1660789905/jrwcddcfkyt4fiyrfatd.jpg",
                      "action": {
                        "link": "swiggydiners://fullScreenGallery/401186?imageId=v1660789905/jrwcddcfkyt4fiyrfatd.jpg&apiCall=true",
                        "type": "DEEPLINK"
                      },
                      "analytics": {
                        "screenName": "DO-Detail",
                        "context": "{\"photo_id\":\"2022-08-18T02:31:42.787\",\"click_position\":1,\"click_on_indicator_+\":false}",
                        "objectValue": "401186",
                        "clickObjectName": "photos"
                      }
                    },
                    "style": {
                      "width": 0.611,
                      "height": 0.586,
                      "left": 0.0333
                    },
                    "mediaItemCornerRadius": {
                      "topLeft": 16,
                      "topRight": 16,
                      "bottomLeft": 16,
                      "bottomRight": 16
                    }
                  },
                  {
                    "imageCardInfo": {
                      "id": "2022-08-18T02:31:47.077",
                      "imageId": "v1660789909/hgrzel4cmwwdh7pgopu8.jpg",
                      "action": {
                        "link": "swiggydiners://fullScreenGallery/401186?imageId=v1660789909/hgrzel4cmwwdh7pgopu8.jpg&apiCall=true",
                        "type": "DEEPLINK"
                      },
                      "analytics": {
                        "screenName": "DO-Detail",
                        "context": "{\"photo_id\":\"2022-08-18T02:31:47.077\",\"click_position\":2,\"click_on_indicator_+\":false}",
                        "objectValue": "401186",
                        "clickObjectName": "photos"
                      }
                    },
                    "style": {
                      "width": 0.288,
                      "height": 0.277,
                      "left": 0.675
                    },
                    "mediaItemCornerRadius": {
                      "topLeft": 16,
                      "topRight": 16,
                      "bottomLeft": 16,
                      "bottomRight": 16
                    }
                  },
                  {
                    "imageCardInfo": {
                      "id": "2022-08-18T02:31:50.967",
                      "imageId": "v1660789913/wzmg0iqbl1bpbnuvrfn5.jpg",
                      "action": {
                        "link": "swiggydiners://fullScreenGallery/401186?imageId=v1660789913/wzmg0iqbl1bpbnuvrfn5.jpg&apiCall=true",
                        "type": "DEEPLINK"
                      },
                      "analytics": {
                        "screenName": "DO-Detail",
                        "context": "{\"photo_id\":\"2022-08-18T02:31:50.967\",\"click_position\":3,\"click_on_indicator_+\":false}",
                        "objectValue": "401186",
                        "clickObjectName": "photos"
                      }
                    },
                    "style": {
                      "width": 0.288,
                      "height": 0.277,
                      "top": 0.307,
                      "left": 0.675
                    },
                    "mediaItemCornerRadius": {
                      "topLeft": 16,
                      "topRight": 16,
                      "bottomLeft": 16,
                      "bottomRight": 16
                    }
                  },
                  {
                    "imageCardInfo": {
                      "id": "2022-08-18T02:31:55.051",
                      "imageId": "v1660789918/hn93hnqsqp4hu0tllez0.jpg",
                      "action": {
                        "link": "swiggydiners://fullScreenGallery/401186?imageId=v1660789918/hn93hnqsqp4hu0tllez0.jpg&apiCall=true",
                        "type": "DEEPLINK"
                      },
                      "analytics": {
                        "screenName": "DO-Detail",
                        "context": "{\"photo_id\":\"2022-08-18T02:31:55.051\",\"click_position\":4,\"click_on_indicator_+\":false}",
                        "objectValue": "401186",
                        "clickObjectName": "photos"
                      }
                    },
                    "style": {
                      "width": 0.288,
                      "height": 0.277,
                      "top": 0.618,
                      "left": 0.0333
                    },
                    "mediaItemCornerRadius": {
                      "topLeft": 16,
                      "topRight": 16,
                      "bottomLeft": 16,
                      "bottomRight": 16
                    }
                  },
                  {
                    "imageCardInfo": {
                      "id": "2022-08-18T02:32:42.973",
                      "imageId": "v1660789965/yxurqq07huvbgssipl22.jpg",
                      "action": {
                        "link": "swiggydiners://fullScreenGallery/401186?imageId=v1660789965/yxurqq07huvbgssipl22.jpg&apiCall=true",
                        "type": "DEEPLINK"
                      },
                      "analytics": {
                        "screenName": "DO-Detail",
                        "context": "{\"photo_id\":\"2022-08-18T02:32:42.973\",\"click_position\":5,\"click_on_indicator_+\":false}",
                        "objectValue": "401186",
                        "clickObjectName": "photos"
                      }
                    },
                    "style": {
                      "width": 0.288,
                      "height": 0.277,
                      "top": 0.618,
                      "left": 0.357
                    },
                    "mediaItemCornerRadius": {
                      "topLeft": 16,
                      "topRight": 16,
                      "bottomLeft": 16,
                      "bottomRight": 16
                    }
                  },
                  {
                    "imageCardInfo": {
                      "id": "2022-08-18T02:32:46.976",
                      "imageId": "v1660789969/mngbuwbmwlsljwpuazsd.jpg",
                      "action": {
                        "link": "swiggydiners://gallery/401186",
                        "type": "DEEPLINK"
                      },
                      "analytics": {
                        "screenName": "DO-Detail",
                        "context": "{\"photo_id\":\"2022-08-18T02:32:46.976\",\"click_position\":6,\"click_on_indicator_+\":true}",
                        "objectValue": "401186",
                        "clickObjectName": "photos"
                      }
                    },
                    "style": {
                      "width": 0.288,
                      "height": 0.277,
                      "top": 0.618,
                      "left": 0.675
                    },
                    "overlay": {
                      "textInfo": {
                        "info": "+4",
                        "color": "white",
                        "font": "FONT_NAME_V2_SUBHEADING1_NEUTRAL_BOLD"
                      },
                      "backgroundColor": "#9902060C"
                    },
                    "mediaItemCornerRadius": {
                      "topLeft": 16,
                      "topRight": 16,
                      "bottomLeft": 16,
                      "bottomRight": 16
                    }
                  }
                ],
                "layout": {
                  "widgetPadding": {
                    "bottom": 12
                  },
                  "scrollBar": {
                    "width": 54,
                    "height": 4
                  },
                  "widgetTheme": {
                    "defaultMode": {
                      "backgroundColour": "#FFFFFF",
                      "theme": "THEME_TYPE_LIGHT",
                      "themeVariant": "THEME_VARIANT_DEFAULT"
                    },
                    "darkMode": {
                      "backgroundColour": "#FFFFFF",
                      "theme": "THEME_TYPE_DARK",
                      "themeVariant": "THEME_VARIANT_DEFAULT"
                    }
                  }
                },
                "id": "dineoutRdpHexaPhotosWidget",
                "header": {
                  "title": "Photos",
                  "headerStyling": {
                    "padding": {
                      "left": 16,
                      "top": 24,
                      "bottom": 8
                    },
                    "titleFontName": "FONT_NAME_BODY_B1_BOLD"
                  },
                  "analytics": {
                    "screenName": "DO-Detail",
                    "context": "{\"photo_count\":10,\"photos_shown_count\":6,\"photo_ids\":[\"2022-08-18T02:31:42.787\",\"2022-08-18T02:31:47.077\",\"2022-08-18T02:31:50.967\",\"2022-08-18T02:31:55.051\",\"2022-08-18T02:32:42.973\",\"2022-08-18T02:32:46.976\",\"2022-08-18T02:32:50.764\",\"2022-08-18T02:32:54.489\",\"2022-08-18T02:32:59.089\",\"2022-08-18T02:33:02.629\"]}",
                    "objectValue": "401186",
                    "impressionObjectName": "photos"
                  },
                  "collapseConfig": {
                    "enabled": true,
                    "collapseIcon": "chevron_down_12",
                    "expandIcon": "chevron_up_12"
                  }
                },
                "scrollAnchor": {
                  "id": "photos"
                }
              }
            }
          },
          {
            "card": {
              "card": {
                "@type": "type.googleapis.com/swiggy.presentation.dinersone.v1.RestaurantHighlights",
                "title": "Amenities (2)",
                "element": [
                  "Parking available",
                  "SwiggyPay accepted"
                ],
                "content": [
                  {
                    "info": "Parking available",
                    "icon": "dineout/details/rx_highlight_star.png"
                  },
                  {
                    "info": "SwiggyPay accepted",
                    "icon": "dineout/details/rx_highlight_star.png"
                  }
                ],
                "rowCount": 2,
                "colCount": 1,
                "scrollAnchor": {
                  "id": "about"
                }
              }
            }
          },
          {
            "card": {
              "card": {
                "@type": "type.googleapis.com/swiggy.gandalf.widgets.v2.TextInfoWidget",
                "title": {
                  "info": "Location",
                  "color": "text_color_highest_emphasis"
                },
                "description": {
                  "info": "5.9 km • 501, Vsr, Cmh Road, Bangalore -38",
                  "color": "text_color_high_emphasis",
                  "font": "FONT_NAME_BODY_B2_REG"
                },
                "iconUrl": "dineout/details/direction.png",
                "cta": {
                  "link": "https://www.google.com/maps/dir/?api=1&origin=12.9716,77.5946&destination=12.978657,77.64357999999993&travelmode=driving",
                  "text": "MAP_DEEPLINK",
                  "type": "MAPS_DIRECTION"
                },
                "scrollAnchor": {
                  "id": "about"
                },
                "metaInfo": {
                  "lng": "77.64357999999993",
                  "showMap": "true",
                  "lat": "12.978657"
                }
              }
            }
          },
          {
            "card": {
              "card": {
                "@type": "type.googleapis.com/swiggy.presentation.dinersone.v1.CtaList",
                "ctas": [
                  {
                    "link": "swiggydiners://login",
                    "text": "Login to avail offer & pay",
                    "type": "primary",
                    "metaInfo": {}
                  }
                ]
              }
            }
          }
        ],
        "firstOffsetRequest": true
      }
    }
  }
}